Metadata-Version: 1.0
Name: distribuciones-jjm
Version: 0.1
Summary: Gaussian distributions
Home-page: UNKNOWN
Author: Juan José Moreno
Author-email: juanjosemorenoc@yahoo.com
License: UNKNOWN
Platform: UNKNOWN
